syncmymoodle/__init__.py
syncmymoodle/__main__.py
syncmymoodle-0.3.0.dist-info/licenses/LICENSE
syncmymoodle-0.3.0.dist-info/METADATA
syncmymoodle-0.3.0.dist-info/WHEEL
syncmymoodle-0.3.0.dist-info/entry_points.txt
syncmymoodle-0.3.0.dist-info/top_level.txt
syncmymoodle-0.3.0.dist-info/RECORD
