Metadata-Version: 2.4
Name: syncMyMoodle
Version: 0.3.0
Summary: Synchronization client for RWTH Moodle
Author-email: Nils Kattenbeck <nilskemail+pypi@gmail.com>
License: GPL-3.0-only
Project-URL: Homepage, https://github.com/Romern/syncMyMoodle
Project-URL: Bug Tracker, https://github.com/Romern/syncMyMoodle/issues
Keywords: moodle,sync,rwth,cli
Classifier: Programming Language :: Python :: 3
Classifier: License :: OSI Approved :: GNU General Public License v3 (GPLv3)
Classifier: Operating System :: OS Independent
Classifier: Development Status :: 5 - Production/Stable
Requires-Python: >=3.11
License-File: LICENSE
Requires-Dist: requests>=2.0.0
Requires-Dist: beautifulsoup4>=4.0.0
Requires-Dist: yt-dlp>=2021.12.27
Requires-Dist: tqdm>=4.0.0
Requires-Dist: lxml>=5.0.0
Provides-Extra: quiz
Requires-Dist: pdfkit>=0.6.0; extra == "quiz"
Provides-Extra: keyring
Requires-Dist: keyring>=20.0.0; extra == "keyring"
Provides-Extra: test
Requires-Dist: black; extra == "test"
Requires-Dist: isort; extra == "test"
Requires-Dist: flake8; extra == "test"
Requires-Dist: flake8-bugbear; extra == "test"
Requires-Dist: mypy; extra == "test"
Requires-Dist: types-requests; extra == "test"
Dynamic: license-file
